MANIFEST.in
setup.py
adApkTools.egg-info/PKG-INFO
adApkTools.egg-info/SOURCES.txt
adApkTools.egg-info/dependency_links.txt
adApkTools.egg-info/top_level.txt
adapktools/__init__.py
adapktools/tools.py
adapktools/lib/linux/aapt
adapktools/lib/linux/apksigner
adapktools/lib/linux/apksigner.jar
adapktools/lib/linux/zipalign
adapktools/lib/linux/lib64/libLLVM.so
adapktools/lib/linux/lib64/libbcc.so
adapktools/lib/linux/lib64/libbcinfo.so
adapktools/lib/linux/lib64/libc++.so
adapktools/lib/linux/lib64/libclang.so
adapktools/lib/windows/aapt.exe
adapktools/lib/windows/apksigner.jar
adapktools/lib/windows/zipalign.exe