Metadata-Version: 1.0
Name: adApkTools
Version: 1.0.6
Summary: An ad channel apk generator
Home-page: https://github.com/Carlos-Zen/adApkTools
Author: CarlosZen
Author-email: lianmezhi@qq.com
License: MIT Licence
Keywords: channel,adApkTools,apk channel
Platform: any
